practica_kraken/__init__.py
practica_kraken/app.py
practica_kraken/assets/favicon.ico
practica_kraken/assets/style.css
practica_kraken/kraken.py
practica_kraken-0.1.3.dist-info/LICENSE
practica_kraken-0.1.3.dist-info/WHEEL
practica_kraken-0.1.3.dist-info/METADATA
practica_kraken-0.1.3.dist-info/RECORD
