Metadata-Version: 2.1
Name: practica-kraken
Version: 0.1.3
Summary: 
Author: Your Name
Author-email: you@example.com
Requires-Python: >=3.8,<4.0
Classifier: Programming Language :: Python :: 3
Classifier: Programming Language :: Python :: 3.10
Classifier: Programming Language :: Python :: 3.8
Classifier: Programming Language :: Python :: 3.9
Requires-Dist: dash (>=2.0.0,<3.0.0)
Requires-Dist: flake8 (>=4.0.1,<5.0.0)
Requires-Dist: krakenex (>=2.1.0,<3.0.0)
Requires-Dist: pandas (>=1.3.4,<2.0.0)
Requires-Dist: pykrakenapi (>=0.2.3,<0.3.0)
